LibraCodex.py
LibraCodex-0.3.dist-info/METADATA
LibraCodex-0.3.dist-info/WHEEL
LibraCodex-0.3.dist-info/license.txt
LibraCodex-0.3.dist-info/top_level.txt
LibraCodex-0.3.dist-info/RECORD
