Metadata-Version: 2.1
Name: LibraCodex
Version: 0.3
Summary: a simple library fot local files management by collect multiple paths in once times.
Author: Norlize
Author-email: norlizyber0@gmail.com
Project-URL: Source code, https://github.com/Norlize/Libracodex
Keywords: local,Libra,Libra codex,LibraCodex,Codex,os,utility,codex,Libracodex,local utility
Classifier: Programming Language :: Python :: 3
Classifier: License :: OSI Approved :: MIT License
Classifier: Operating System :: OS Independent
License-File: license.txt
